{
  "kind": "collectionType",
  "collectionName": "tags",
  "info": {
    "singularName": "tag",
    "pluralName": "tags",
    "displayName": "Tag",
    "description": ""
  },
  "options": {
    "draftAndPublish": false
  },
  "attributes": {
    "title": {
      "type": "string"
    },
    "isNew": {
      "type": "boolean"
    },
    "isOnSale": {
      "type": "boolean"
    },
    "products": {
      "type": "relation",
      "relation": "manyToMany",
      "target": "api::product.product",
      "inversedBy": "tags"
    }
  }
}
